{
  "_format": "hh-sol-cache-2",
  "files": {
    "/home/carla/Proyectos/eth/hardhat101/contracts/Counter.sol": {
      "lastModificationDate": 1606678560079,
      "contentHash": "23b631f4876531883c65dba807a093ea",
      "sourceName": "contracts/Counter.sol",
      "solcConfig": {
        "version": "0.6.8",
        "settings": {
          "optimizer": {
            "enabled": false,
            "runs": 200
          },
          "outputSelection": {
            "*": {
              "*": [
                "abi",
                "evm.bytecode",
                "evm.deployedBytecode",
                "evm.methodIdentifiers"
              ],
              "": [
                "ast"
              ]
            }
          }
        }
      },
      "imports": [
        "hardhat/console.sol"
      ],
      "versionPragmas": [
        "^0.6.8"
      ],
      "artifacts": [
        "Counter"
      ]
    },
    "/home/carla/Proyectos/eth/hardhat101/node_modules/hardhat/console.sol": {
      "lastModificationDate": 1606676391149,
      "contentHash": "c20b2460755f312099ccd61427237ded",
      "sourceName": "hardhat/console.sol",
      "solcConfig": {
        "version": "0.7.3",
        "settings": {
          "optimizer": {
            "enabled": false,
            "runs": 200
          },
          "outputSelection": {
            "*": {
              "*": [
                "abi",
                "evm.bytecode",
                "evm.deployedBytecode",
                "evm.methodIdentifiers"
              ],
              "": [
                "ast"
              ]
            }
          }
        }
      },
      "imports": [],
      "versionPragmas": [
        ">=0.4.22 <0.8.0"
      ],
      "artifacts": [
        "console"
      ]
    },
    "/home/carla/Proyectos/eth/hardhat101/contracts/Token.sol": {
      "lastModificationDate": 1606677121796,
      "contentHash": "cf98a1fc4acb60b7ed6fade4816f023d",
      "sourceName": "contracts/Token.sol",
      "solcConfig": {
        "version": "0.7.3",
        "settings": {
          "optimizer": {
            "enabled": false,
            "runs": 200
          },
          "outputSelection": {
            "*": {
              "*": [
                "abi",
                "evm.bytecode",
                "evm.deployedBytecode",
                "evm.methodIdentifiers"
              ],
              "": [
                "ast"
              ]
            }
          }
        }
      },
      "imports": [
        "hardhat/console.sol"
      ],
      "versionPragmas": [
        "^0.7.0"
      ],
      "artifacts": [
        "Token"
      ]
    }
  }
}
